{
  "collectCoverageFrom": [
    "src/**/*.{js,vue}"
  ],
  "coverageReporters": [
    "cobertura",
    "json",
    "lcov",
    "text",
    "clover"
  ],
  "moduleFileExtensions": [
    "js",
    "json",
    "vue"
  ],
  "moduleNameMapper": {
    "^@/(.*)$": "<rootDir>/src/$1"
  },
  "snapshotSerializers": [
    "<rootDir>/node_modules/jest-serializer-vue"
  ],
  "testMatch": [
    "**/__tests__/**/(*.)+(spec|test).js"
  ],
  "transform": {
    "^.+\\.js$": "<rootDir>/node_modules/babel-jest",
    ".*\\.(vue)$": "<rootDir>/node_modules/vue-jest"
  }
}
